dyntwist/__init__.py
dyntwist/dyntwist.py
dyntwist/dyn_lists/afraid_freedns_domains.txt
dyntwist/dyn_lists/changeip_domains.txt
dyntwist/dyn_lists/duckdns_domain.txt
dyntwist/dyn_lists/dyn.com_domains.txt
dyntwist/dyn_lists/dynu_domains.txt
dyntwist/dyn_lists/noip_domains.txt
dyntwist/dyn_lists/now-dns_domains.txt
dyntwist/dyn_lists/oray_domains.txt
dyntwist/dyn_lists/pubyun_domains.txt
dyntwist-1.4.0.dist-info/METADATA
dyntwist-1.4.0.dist-info/WHEEL
dyntwist-1.4.0.dist-info/top_level.txt
dyntwist-1.4.0.dist-info/RECORD
