Metadata-Version: 2.1
Name: dyntwist
Version: 1.4.0
Summary: Discover resolving dynamic DNS domains based on keywords.
Home-page: https://github.com/wesinator/dyntwist
Author: wesinator
Author-email: 13hurdw@gmail.com
License: UNKNOWN
Platform: UNKNOWN
Classifier: Intended Audience :: Developers
Classifier: License :: OSI Approved :: GNU Affero General Public License v3 or later (AGPLv3+)
Classifier: Natural Language :: English
Classifier: Programming Language :: Python :: 3
Requires-Dist: nslookup
